createpypkg/__init__.py
createpypkg/cli/__init__.py
createpypkg/cli/main.py
createpypkg/cli/util.py
createpypkg/static/Python.gitignore
createpypkg/template/Dockerfile.j2
createpypkg/template/MANIFEST.in.j2
createpypkg/template/README.md.j2
createpypkg/template/__init__.py.j2
createpypkg/template/cli.py.j2
createpypkg/template/docker-compose.yml.j2
createpypkg/template/pyproject.toml.j2
create_pypkg-0.2.0.dist-info/LICENSE
create_pypkg-0.2.0.dist-info/METADATA
create_pypkg-0.2.0.dist-info/WHEEL
create_pypkg-0.2.0.dist-info/entry_points.txt
create_pypkg-0.2.0.dist-info/top_level.txt
create_pypkg-0.2.0.dist-info/RECORD
