Metadata-Version: 2.1
Name: create-pypkg
Version: 0.2.0
Summary: Python package scaffold builder
Author-email: Daichi Narushima <dnarsil+github@gmail.com>
Maintainer-email: Daichi Narushima <dnarsil+github@gmail.com>
License: MIT License
Project-URL: repository, https://github.com/dceoy/create-pypkg.git
Classifier: Development Status :: 4 - Beta
Classifier: Environment :: Console
Classifier: License :: OSI Approved :: MIT License
Classifier: Operating System :: OS Independent
Classifier: Programming Language :: Python
Classifier: Programming Language :: Python :: 3
Classifier: Topic :: Software Development
Requires-Python: >=3.10
License-File: LICENSE
Requires-Dist: docopt >=0.6.2
Requires-Dist: jinja2 >=3.1.2
